Metadata-Version: 2.1
Name: ue5-distributions
Version: 0.2
Summary: Gaussian and Binomial distributions
Home-page: UNKNOWN
License: UNKNOWN
Platform: UNKNOWN
